petsseries/__init__.py
petsseries/api.py
petsseries/auth.py
petsseries/config.py
petsseries/constants.py
petsseries/crypto.py
petsseries/decorators.py
petsseries/devices.py
petsseries/discovery.py
petsseries/dp_codes.py
petsseries/events.py
petsseries/exceptions.py
petsseries/homes.py
petsseries/meals.py
petsseries/models.py
petsseries/session.py
petsseries/tuya.py
petsseries-0.3.0.dist-info/METADATA
petsseries-0.3.0.dist-info/WHEEL
petsseries-0.3.0.dist-info/top_level.txt
petsseries-0.3.0.dist-info/RECORD
