Metadata-Version: 2.4
Name: petsseries
Version: 0.3.0
Summary: A Unofficial Python client for interacting with the Philips Pets Series API
Home-page: https://github.com/abovecolin/petsseries
Author: AboveColin
Author-email: colin@cdevries.dev
Classifier: Programming Language :: Python :: 3
Classifier: Operating System :: OS Independent
Requires-Python: >=3.11
Requires-Dist: aiohttp
Requires-Dist: aiofiles
Requires-Dist: certifi
Requires-Dist: PyJWT
Requires-Dist: tinytuya
Requires-Dist: cryptography
Dynamic: author
Dynamic: author-email
Dynamic: classifier
Dynamic: description
Dynamic: description-content-type
Dynamic: home-page
Dynamic: requires-dist
Dynamic: requires-python
Dynamic: summary
